napari_brushsettings/__init__.py
napari_brushsettings/_dock_widget.py
napari_brushsettings/_tests/__init__.py
napari_brushsettings/_tests/test_dock_widget.py
napari_brushsettings-0.0.2.dist-info/LICENSE
napari_brushsettings-0.0.2.dist-info/METADATA
napari_brushsettings-0.0.2.dist-info/WHEEL
napari_brushsettings-0.0.2.dist-info/entry_points.txt
napari_brushsettings-0.0.2.dist-info/top_level.txt
napari_brushsettings-0.0.2.dist-info/RECORD
